scripts/Example_CommandsFromScratch.txt
scripts/__init__.py
scripts/defineAndCountClades.py
scripts/drawMuller.py
scripts/extractCoding.py
scripts/mutationLinages_report.py
scripts/parse.py
scripts/parseFastaNames.py
scripts/treeClass.py
epimuller-0.0.8.dist-info/LICENSE.txt
epimuller-0.0.8.dist-info/METADATA
epimuller-0.0.8.dist-info/WHEEL
epimuller-0.0.8.dist-info/entry_points.txt
epimuller-0.0.8.dist-info/top_level.txt
epimuller-0.0.8.dist-info/RECORD
