Metadata-Version: 2.1
Name: epimuller
Version: 0.0.8
Summary: Visualize lineages overtime, with phylogentic context, based on viral genomes
Home-page: https://github.com/jennifer-bio/epimuller
Author: Jennifer L Havens
Author-email: jhavens@ucsd.edu
License: MIT license
Keywords: epimuller
Platform: UNKNOWN
Classifier: Development Status :: 2 - Pre-Alpha
Classifier: Intended Audience :: Science/Research
Classifier: Intended Audience :: Healthcare Industry
Classifier: License :: OSI Approved :: MIT License
Classifier: Natural Language :: English
Classifier: Programming Language :: Python :: 3.7
Classifier: Programming Language :: Python :: 3.8
Classifier: Programming Language :: Python :: 3.9
Classifier: Topic :: Scientific/Engineering :: Bio-Informatics
Classifier: Topic :: Scientific/Engineering :: Visualization
Requires-Python: >=3.7
Requires-Dist: ete3
Requires-Dist: datetime
Requires-Dist: statistics
Requires-Dist: svgwrite
Requires-Dist: pycairo (<=1.20.0)
Requires-Dist: cairosvg
Requires-Dist: argparse
Requires-Dist: numpy
Requires-Dist: six
